[
  {
    "id": "santander",
    "name": "Santander Bank Polska S.A.",
    "legalName": "Santander Bank Polska Spółka Akcyjna",
    "krs": "0000008723",
    "nip": "8960005765",
    "address": "ul. Strzegomska 42c, 53-611 Wrocław",
    "formerNames": ["BZ WBK S.A.", "Kredyt Bank S.A."]
  },
  {
    "id": "pko",
    "name": "PKO Bank Polski S.A.",
    "legalName": "Powszechna Kasa Oszczędności Bank Polski Spółka Akcyjna",
    "krs": "0000026438",
    "nip": "5250007738",
    "address": "ul. Puławska 15, 02-515 Warszawa",
    "formerNames": []
  },
  {
    "id": "mbank",
    "name": "mBank S.A.",
    "legalName": "mBank Spółka Akcyjna",
    "krs": "0000025237",
    "nip": "5260215088",
    "address": "ul. Prosta 18, 00-850 Warszawa",
    "formerNames": ["BRE Bank S.A."]
  },
  {
    "id": "ing",
    "name": "ING Bank Śląski S.A.",
    "legalName": "ING Bank Śląski Spółka Akcyjna",
    "krs": "0000005459",
    "nip": "6340135475",
    "address": "ul. Sokolska 34, 40-086 Katowice",
    "formerNames": []
  },
  {
    "id": "millennium",
    "name": "Bank Millennium S.A.",
    "legalName": "Bank Millennium Spółka Akcyjna",
    "krs": "0000010186",
    "nip": "5260214850",
    "address": "ul. Stanisława Żaryna 2A, 02-593 Warszawa",
    "formerNames": []
  },
  {
    "id": "pekao",
    "name": "Bank Pekao S.A.",
    "legalName": "Bank Polska Kasa Opieki Spółka Akcyjna",
    "krs": "0000014843",
    "nip": "5260006841",
    "address": "ul. Grzybowska 53/57, 00-844 Warszawa",
    "formerNames": []
  },
  {
    "id": "bnp",
    "name": "BNP Paribas Bank Polska S.A.",
    "legalName": "BNP Paribas Bank Polska Spółka Akcyjna",
    "krs": "0000011571",
    "nip": "5260009105",
    "address": "ul. Kasprzaka 2, 01-211 Warszawa",
    "formerNames": ["BGŻ BNP Paribas S.A.", "Bank BGŻ S.A."]
  },
  {
    "id": "alior",
    "name": "Alior Bank S.A.",
    "legalName": "Alior Bank Spółka Akcyjna",
    "krs": "0000305178",
    "nip": "1070010731",
    "address": "ul. Łopuszańska 38D, 02-232 Warszawa",
    "formerNames": []
  },
  {
    "id": "credit-agricole",
    "name": "Credit Agricole Bank Polska S.A.",
    "legalName": "Credit Agricole Bank Polska Spółka Akcyjna",
    "krs": "0000039887",
    "nip": "6570082274",
    "address": "pl. Orląt Lwowskich 1, 53-605 Wrocław",
    "formerNames": ["Lukas Bank S.A."]
  },
  {
    "id": "citi",
    "name": "Bank Handlowy w Warszawie S.A.",
    "legalName": "Bank Handlowy w Warszawie Spółka Akcyjna",
    "krs": "0000001538",
    "nip": "5260300291",
    "address": "ul. Senatorska 16, 00-923 Warszawa",
    "formerNames": ["Citi Handlowy"]
  },
  {
    "id": "getin",
    "name": "VeloBank S.A. (d. Getin Noble Bank)",
    "legalName": "VeloBank Spółka Akcyjna",
    "krs": "0000991173",
    "nip": "7011105189",
    "address": "ul. Rondo Ignacego Daszyńskiego 2C, 00-843 Warszawa",
    "formerNames": ["Getin Noble Bank S.A.", "Getin Bank S.A.", "Noble Bank S.A."]
  },
  {
    "id": "bos",
    "name": "BOŚ Bank S.A.",
    "legalName": "Bank Ochrony Środowiska Spółka Akcyjna",
    "krs": "0000015525",
    "nip": "5270204036",
    "address": "ul. Żelazna 32, 00-832 Warszawa",
    "formerNames": []
  },
  {
    "id": "deutsche",
    "name": "Deutsche Bank Polska S.A.",
    "legalName": "Deutsche Bank Polska Spółka Akcyjna",
    "krs": "0000022493",
    "nip": "6760070700",
    "address": "al. Armii Ludowej 26, 00-609 Warszawa",
    "formerNames": []
  }
]
